aiosqlcipher/__init__.py
aiosqlcipher/context.py
aiosqlcipher/core.py
aiosqlcipher/cursor.py
aiosqlcipher/py.typed
aiosqlcipher/tests/__init__.py
aiosqlcipher/tests/__main__.py
aiosqlcipher/tests/helpers.py
aiosqlcipher/tests/perf.py
aiosqlcipher/tests/smoke.py
aiosqlcipher-0.1.0.dist-info/licenses/LICENSE
aiosqlcipher-0.1.0.dist-info/METADATA
aiosqlcipher-0.1.0.dist-info/WHEEL
aiosqlcipher-0.1.0.dist-info/top_level.txt
aiosqlcipher-0.1.0.dist-info/RECORD
