Metadata-Version: 2.4
Name: aiosqlcipher
Version: 0.1.0
Summary: Python asyncio bindings for SQLCipher
Author-email: tianqing <tianqing108@126.com>
License: MIT License
Project-URL: Github, https://github.com/tianqing108/aiosqlcipher
Classifier: Development Status :: 5 - Production/Stable
Classifier: Framework :: AsyncIO
Classifier: Intended Audience :: Developers
Classifier: License :: OSI Approved :: MIT License
Classifier: Topic :: Software Development :: Libraries
Requires-Python: >=3.9
License-File: LICENSE
Requires-Dist: sqlcipher3-wheels>=0.5.4.post0
Requires-Dist: typing_extensions>=4.0
Dynamic: license-file
